[{"Usuario":"Britany","Comprobantes":[],"Billeteras":[],"ID":"USclRTTV0cdevcuX","Contraseña":"suerteConMate"},{"Usuario":"Nakko","Comprobantes":[],"Billeteras":[],"ID":"USo6vttimOZ4e2mo","Contraseña":"dsa321"},{"Usuario":"Rouse","Comprobantes":[{"Banco Destino":{"CVU":"4751089145821541870074","Banco":"Bna","Alias":"Felicidad.Pantalón"},"Fecha":"01/06/1991","Banco Origen":{"CVU":"5311865597666891977730","Banco":"Prex","Alias":"Cogollo.Reloj"},"Monto":1249.773274443773,"EstadoTransferencia":"Rechazado","EstadoComprobante":"Archivado","ID":"CP5hUI6LbJrXALbl","CodigoTransferencia":"043960785497"},{"Banco Destino":{"CVU":"9717536646617083920566","Banco":"Banco supervielle","Alias":"Flota.Gato"},"Fecha":"01/10/2021","Banco Origen":{"CVU":"0594456823970474572912","Banco":"Mercado pago","Alias":"Alfajor.Horizonte"},"Monto":215063.3488433594,"EstadoTransferencia":"Enviado","EstadoComprobante":"Confirmado","ID":"CP8Xav0C040kKdSW","CodigoTransferencia":"812835134315"},{"Banco Destino":{"CVU":"9744207730897410023379","Banco":"Cuenta dni","Alias":"Escoba.Mochila"},"Fecha":"01/05/1991","Banco Origen":{"CVU":"1788285014640489508274","Banco":"Cuenta dni","Alias":"Tiburón.Entero"},"Monto":22687.26665369769,"EstadoTransferencia":"Enviado","EstadoComprobante":"Confirmado","ID":"CPGm6qsTOicca9PN","CodigoTransferencia":"506553701440"},{"Banco Destino":{"CVU":"7111923726819735842540","Banco":"Brubank","Alias":"Alma.Hacker"},"Fecha":"01/02/2024","Banco Origen":{"CVU":"5649059820117439453755","Banco":"Uala","Alias":"Canguro.Escoba"},"Monto":213441.4336445124,"EstadoTransferencia":"Enviado","EstadoComprobante":"Confirmado","ID":"CPWtyAmuYXVChxT6","CodigoTransferencia":"057382420718"},{"Banco Destino":{"CVU":"7815017376849494870253","Banco":"Personal pay","Alias":"Cucurucho.Pantalón"},"Fecha":"01/05/1986","Banco Origen":{"CVU":"0399242036235348894636","Banco":"Banco supervielle","Alias":"Flores.Arado"},"Monto":114086.09771133283,"EstadoTransferencia":"Rechazado","EstadoComprobante":"Archivado","ID":"CPBtrMPqOzDMkf3r","CodigoTransferencia":"341394025111"},{"Banco Destino":{"CVU":"3701373175690341709875","Banco":"Personal pay","Alias":"Canguro.Biceps"},"Fecha":"01/10/1979","Banco Origen":{"CVU":"9131266811327232797485","Banco":"Naranja x","Alias":"Aluminio.Hacker"},"Monto":130816.1199474173,"EstadoTransferencia":"Enviado","EstadoComprobante":"Confirmado","ID":"CPBa0ARXwvERubEU","CodigoTransferencia":"027733789326"},{"Banco Destino":{"CVU":"0851702215254341025805","Banco":"Mercado pago","Alias":"Basto.Felicidad"},"Fecha":"01/02/2005","Banco Origen":{"CVU":"0686132250316031712539","Banco":"Banco frances","Alias":"Flecha.Gato"},"Monto":128209.52310691323,"EstadoTransferencia":"Pendiente","EstadoComprobante":"Archivado","ID":"CPvr8h6lCaq9C06h","CodigoTransferencia":"810140253666"},{"Banco Destino":{"CVU":"2633487923619089657747","Banco":"Banco frances","Alias":"Flota.Tinta"},"Fecha":"01/06/2022","Banco Origen":{"CVU":"5125461029054761600887","Banco":"Modo","Alias":"Amarillo.Mesa"},"Monto":249756.75143922563,"EstadoTransferencia":"Enviado","EstadoComprobante":"Confirmado","ID":"CP90u7Gi0pW4tWk6","CodigoTransferencia":"925265771087"},{"Banco Destino":{"CVU":"2963760359607560389585","Banco":"Prex","Alias":"Flota.Funcionario"},"Fecha":"01/04/2022","Banco Origen":{"CVU":"5918277597354796692636","Banco":"Prex","Alias":"Cantar.Fino"},"Monto":27190.886274459892,"EstadoTransferencia":"Enviado","EstadoComprobante":"Confirmado","ID":"CPgFU6sIWCRi25vj","CodigoTransferencia":"424181957117"},{"Banco Destino":{"CVU":"3745878854517075893984","Banco":"Mercado pago","Alias":"Vestuario.Corazón"},"Fecha":"01/09/2010","Banco Origen":{"CVU":"3532985087033576451454","Banco":"Banco frances","Alias":"Aire.Flota"},"Monto":135023.57406325295,"EstadoTransferencia":"Pendiente","EstadoComprobante":"Archivado","ID":"CPSJWIvhf19w2W98","CodigoTransferencia":"946220930433"},{"Banco Destino":{"CVU":"8571842299018726703202","Banco":"Banco supervielle","Alias":"Cirujano.Lobo"},"Fecha":"01/01/2013","Banco Origen":{"CVU":"0095180150940230782005","Banco":"Banco patagonia","Alias":"Fino.Grueso"},"Monto":67040.83850080532,"EstadoTransferencia":"Enviado","EstadoComprobante":"Archivado","ID":"CPsNT7S0RTjImKej","CodigoTransferencia":"174592578038"},{"Banco Destino":{"CVU":"5535018754471404136079","Banco":"Brubank","Alias":"Oficial.Corazón"},"Fecha":"01/12/2014","Banco Origen":{"CVU":"8495796883045612080667","Banco":"Mercado pago","Alias":"Escoba.Tiburón"},"Monto":138532.10972051835,"EstadoTransferencia":"Enviado","EstadoComprobante":"Recibido","ID":"CPTZmA5QdsyJiHWz","CodigoTransferencia":"487599167688"},{"Banco Destino":{"CVU":"2250389037124460025124","Banco":"Personal pay","Alias":"Reina.Abogado"},"Fecha":"01/04/2017","Banco Origen":{"CVU":"5738088594525082267392","Banco":"Mercado pago","Alias":"Pajaro.Juicio"},"Monto":229438.31431299096,"EstadoTransferencia":"Enviado","EstadoComprobante":"Recibido","ID":"CPe4MfJaeDcpxkx4","CodigoTransferencia":"020300166086"}],"Billeteras":[{"Persona":{"Nombre":"Emilio Lorenzo","CUIL":"11-72302459-3","ID":"PSOkgNE5mOS7bnPt"},"Banco":{"CVU":"6872578002077956177141","Banco":"Uala","Alias":"Felicidad.Perro"},"API":"IQidjGQvbWBXjR","ID":"BVbbATAYBGVWxgy1"},{"Persona":{"Nombre":"Vicente Jose Dominguez Nieto","CUIL":"50-39480199-8","ID":"PS2Ob520X4Kn28xr"},"Banco":{"CVU":"7928382183076159306067","Banco":"Banco frances","Alias":"Cogollo.Juicio"},"API":"KabZDeMvaRuS6f","ID":"BVKlx35Ol455SWyh"},{"Persona":{"Nombre":"Facundo Martin Reyes","CUIL":"83-00752691-4","ID":"PSkFZrotPOEMfjf2"},"Banco":{"CVU":"3751523151341813998534","Banco":"Mercado pago","Alias":"Abogado.Turno"},"API":"dveXJnuiLFNCjc","ID":"BVARqq0u4bFBNwNa"},{"Persona":{"Nombre":"Susana Cecilia Diaz Prieto","CUIL":"66-97366047-7","ID":"PSQJ4D7XF0NF7ivP"},"Banco":{"CVU":"9531567207670231130302","Banco":"Prex","Alias":"Tinta.Basto"},"API":"xl0rz0IoQPFu3R","ID":"BVZ1At54Pgo3F33j"}],"ID":"USJ50y0dNRZMUKMU","Contraseña":"Rouse484848@@"}]